.npmignore
MANIFEST.in
package.json
setup.py
webpack.config.js
lib/ReactopyaModel.js
lib/all_widgets.js
lib/embed.js
lib/extension.js
lib/index.js
lib/labplugin.js
reactopya_jup/VERSION
reactopya_jup/__init__.py
reactopya_jup/_version.py
reactopya_jup/reactopyajupyterwidget.py
reactopya_jup.egg-info/PKG-INFO
reactopya_jup.egg-info/SOURCES.txt
reactopya_jup.egg-info/dependency_links.txt
reactopya_jup.egg-info/requires.txt
reactopya_jup.egg-info/top_level.txt
reactopya_jup/static/extension.js
reactopya_jup/static/index.js