Metadata-Version: 1.1
Name: reactopya-jup
Version: 0.7.0
Summary: Reactopya JupyterLab extension
Home-page: UNKNOWN
Author: Jeremy Magland
Author-email: UNKNOWN
License: UNKNOWN
Platform: UNKNOWN
Classifier: Programming Language :: Python :: 3
Classifier: License :: OSI Approved :: Apache Software License
Classifier: Operating System :: OS Independent
